Pyon/__init__.py
pyobjectnotation-1.0.0.dist-info/LICENSE.txt
pyobjectnotation-1.0.0.dist-info/METADATA
pyobjectnotation-1.0.0.dist-info/WHEEL
pyobjectnotation-1.0.0.dist-info/top_level.txt
pyobjectnotation-1.0.0.dist-info/RECORD
