Metadata-Version: 2.2
Name: PyObjectNotation
Version: 1.0.0
Summary: PYON is a simple text-based format for storing structured data. This module allows loading and saving PYON files, converting them into Python dictionaries and vice versa.
Home-page: https://github.com/devlimegames/pyon
Author: DevLimeGames
Author-email: dev.limegames@gmail.com
License: Creative Commons Attribution-NonCommercial 4.0 International
Classifier: Programming Language :: Python :: 3
Classifier: License :: Other/Proprietary License
Classifier: Operating System :: OS Independent
Requires-Python: >=3.6
License-File: LICENSE.txt
Dynamic: author
Dynamic: author-email
Dynamic: classifier
Dynamic: description
Dynamic: description-content-type
Dynamic: home-page
Dynamic: license
Dynamic: requires-python
Dynamic: summary
